skorch_forecasting/__init__.py
skorch_forecasting/exceptions.py
skorch_forecasting/pipelines.py
skorch_forecasting/ensemble/__init__.py
skorch_forecasting/ensemble/_bagging.py
skorch_forecasting/model_selection/__init__.py
skorch_forecasting/model_selection/_split.py
skorch_forecasting/model_selection/_walkforward.py
skorch_forecasting/nn/__init__.py
skorch_forecasting/nn/_pytorchforecasting.py
skorch_forecasting/nn/_seq2seq.py
skorch_forecasting/nn/base.py
skorch_forecasting/nn/datasets.py
skorch_forecasting/preprocessing/__init__.py
skorch_forecasting/preprocessing/_column_selector.py
skorch_forecasting/preprocessing/_data.py
skorch_forecasting/preprocessing/_encoders.py
skorch_forecasting/preprocessing/_pandas_column_transformer.py
skorch_forecasting/utils/__init__.py
skorch_forecasting/utils/data.py
skorch_forecasting/utils/datetime.py
skorch_forecasting/utils/pandas.py
skorch_forecasting/utils/rnn.py
skorch_forecasting/utils/validation.py
skorch_forecasting-0.0.67.dist-info/LICENSE
skorch_forecasting-0.0.67.dist-info/METADATA
skorch_forecasting-0.0.67.dist-info/WHEEL
skorch_forecasting-0.0.67.dist-info/top_level.txt
skorch_forecasting-0.0.67.dist-info/RECORD
