Metadata-Version: 2.1
Name: skorch-forecasting
Version: 0.0.67
Summary: Sklearn interface to state-of-the-art forecasting with neural networks.
Author: ramonamez
Author-email: ramonamez <rameviz@icloud.com>
Project-URL: Homepage, https://github.com/ramonAV98/skorch_forecasting
Classifier: Programming Language :: Python :: 3
Classifier: License :: OSI Approved :: MIT License
Classifier: Operating System :: OS Independent
Requires-Python: >=3.7
License-File: LICENSE
Requires-Dist: numpy (<1.24,>=1.23)
Requires-Dist: pandas (>=1.4.0)
Requires-Dist: scikit-learn (>=1.0.0)
Requires-Dist: skorch (>=0.10.0)
Requires-Dist: torch (>=1.5.0)
Requires-Dist: pytorch-forecasting (>=0.9.0)
